html2json/__init__.py
html2json-0.3.3.dist-info/METADATA
html2json-0.3.3.dist-info/WHEEL
html2json-0.3.3.dist-info/licenses/LICENSE
html2json-0.3.3.dist-info/RECORD
