Metadata-Version: 2.4
Name: html2json
Version: 0.3.3
Summary: Parsing HTML to JSON
Project-URL: Repository, https://github.com/chuanconggao/html2json
Author-email: Chuancong Gao <chuanconggao@users.noreply.github.com>
License-Expression: MIT
License-File: LICENSE
Keywords: html,json,parser
Classifier: Operating System :: OS Independent
Classifier: Programming Language :: Python
Classifier: Programming Language :: Python :: 2
Classifier: Programming Language :: Python :: 3
Requires-Python: >=3.9
Requires-Dist: pyquery>=2.0.1
